kg_efk/__init__.py
kg_efk/builder.py
kg_efk/option.py
kg_efk/py.typed
kg_efk/tests/__init__.py
kg_efk/tests/test_builder.py
kg_efk-0.8.2.dist-info/LICENSE
kg_efk-0.8.2.dist-info/METADATA
kg_efk-0.8.2.dist-info/WHEEL
kg_efk-0.8.2.dist-info/top_level.txt
kg_efk-0.8.2.dist-info/RECORD
